<!DOCTYPE codename-engine-character>
<character sprite="bf-left" antialiasing="false" flipX="true" camx="122" camy="90" isPlayer="true" icon="bf" color="#30B0D1">
	<anim name="idle" anim="idle" fps="8"/>
	<anim name="singDOWN" anim="down0" fps="8"/>
	<anim name="singRIGHT" anim="right0" fps="8"/>
	<anim name="singLEFT" anim="left0" fps="8"/>
	<anim name="singUP" anim="up0" fps="8"/>
	<anim name="singLEFTmiss" anim="leftmiss_flip" fps="8"/>
	<anim name="singDOWNmiss" anim="downmiss_flip" fps="8"/>
	<anim name="singUPmiss" anim="upmiss_flip" fps="8"/>
	<anim name="singRIGHTmiss" anim="rightmiss_flip" fps="8"/>
</character>
